_version.py
declog/__init__.py
declog/core.py
declog/database.py
declog/utils.py
declog/logger/__init__.py
declog/logger/mixins.py
declog-0.5.0.dist-info/LICENSE
declog-0.5.0.dist-info/METADATA
declog-0.5.0.dist-info/WHEEL
declog-0.5.0.dist-info/top_level.txt
declog-0.5.0.dist-info/RECORD
