Metadata-Version: 2.1
Name: declog
Version: 0.5.0
Summary: Minimal boilerplate logger for functions.
Author-email: Josh Read <joshua-read@hotmail.co.uk>
License: MIT License
Project-URL: Documentation, https://josh-read.github.io/declog/
Project-URL: Issues, https://github.com/josh-read/declog/issues
Project-URL: Source, https://github.com/josh-read/declog
Classifier: Programming Language :: Python
Classifier: Programming Language :: Python :: 3.9
Classifier: Programming Language :: Python :: 3.10
Classifier: Programming Language :: Python :: 3.11
Classifier: License :: OSI Approved :: MIT License
Classifier: Operating System :: OS Independent
Requires-Python: >=3.9
License-File: LICENSE
Provides-Extra: dev
Requires-Dist: pytest ; extra == 'dev'
Requires-Dist: pre-commit ; extra == 'dev'
Requires-Dist: black ; extra == 'dev'
Requires-Dist: flake8 ; extra == 'dev'
Requires-Dist: mkdocs ; extra == 'dev'
Requires-Dist: mkdocstrings[python] ; extra == 'dev'
Requires-Dist: mkdocs-material ; extra == 'dev'
